motorframework
